reg_h/__init__.py
reg_h/reg_h.pth
h_ckpt-0.1.dist-info/LICENSE.txt
h_ckpt-0.1.dist-info/METADATA
h_ckpt-0.1.dist-info/WHEEL
h_ckpt-0.1.dist-info/entry_points.txt
h_ckpt-0.1.dist-info/top_level.txt
h_ckpt-0.1.dist-info/zip-safe
h_ckpt-0.1.dist-info/RECORD
