Metadata-Version: 2.1
Name: h_ckpt
Version: 0.1
Summary: Protein chemical shift prediction based on Protein Language Model
Home-page: https://github.com/doorpro/predict-chemical-shifts-from-protein-sequence.git
Author: Zhu He
Author-email: 2260913071@qq.com
Classifier: Programming Language :: Python :: 3
Classifier: License :: OSI Approved :: MIT License
Classifier: Natural Language :: English
Classifier: Operating System :: OS Independent
Classifier: Topic :: Scientific/Engineering :: Bio-Informatics
Classifier: Topic :: Scientific/Engineering :: Artificial Intelligence
License-File: LICENSE.txt
Requires-Dist: torch==2.5.0
Requires-Dist: torchaudio==2.5.0
Requires-Dist: torchvision==0.20.0
Requires-Dist: fair-esm==2.0.0
Requires-Dist: numpy==2.1.2
Requires-Dist: biopython==1.84
Requires-Dist: pandas==2.2.3
